{"_meta":"This note has type `canvas`. It uses excalidraw and stores an exported svg alongside.","elements":[{"type":"rectangle","version":522,"versionNonce":420626769,"isDeleted":false,"id":"sPONRaTVfRenjfc0SyF77","fillStyle":"hachure","strokeWidth":1,"strokeStyle":"solid","roughness":0,"opacity":100,"angle":0,"x":229.71618162800462,"y":-233.2476086641026,"strokeColor":"#000000","backgroundColor":"transparent","width":287.3333740234375,"height":296.0000305175781,"seed":574551537,"groupIds":[],"roundness":null,"boundElements":null,"updated":1696424775188,"link":null,"locked":false},{"type":"line","version":313,"versionNonce":1764358207,"isDeleted":false,"id":"7mJu2ww62Tgk_t3rdhoU-","fillStyle":"hachure","strokeWidth":1,"strokeStyle":"solid","roughness":0,"opacity":100,"angle":0,"x":274.38286863972337,"y":-233.2476391816807,"strokeColor":"#000000","backgroundColor":"transparent","width":0,"height":295.3333435058594,"seed":1573412255,"groupIds":[],"roundness":null,"boundElements":null,"updated":1696424775188,"link":null,"locked":false,"startBinding":null,"endBinding":null,"lastCommittedPoint":null,"startArrowhead":null,"endArrowhead":null,"points":[[0,0],[0,295.3333435058594]]},{"type":"line","version":266,"versionNonce":281014065,"isDeleted":false,"id":"7m-KB0sC_9cGYzJw80akm","fillStyle":"hachure","strokeWidth":1,"strokeStyle":"solid","roughness":0,"opacity":100,"angle":0,"x":318.38286863972337,"y":-232.58095216996196,"strokeColor":"#000000","backgroundColor":"transparent","width":0,"height":294.6666564941406,"seed":128782289,"groupIds":[],"roundness":null,"boundElements":null,"updated":1696424775188,"link":null,"locked":false,"startBinding":null,"endBinding":null,"lastCommittedPoint":null,"startArrowhead":null,"endArrowhead":null,"points":[[0,0],[0,294.6666564941406]]},{"type":"line","version":354,"versionNonce":1323210847,"isDeleted":false,"id":"hCMnTNBF_2kqzkWpJaiUo","fillStyle":"hachure","strokeWidth":1,"strokeStyle":"solid","roughness":0,"opacity":100,"angle":0,"x":361.0495556514421,"y":-232.58095216996196,"strokeColor":"#000000","backgroundColor":"transparent","width":0,"height":294.0000305175781,"seed":1632195007,"groupIds":[],"roundness":null,"boundElements":null,"updated":1696424775188,"link":null,"locked":false,"startBinding":null,"endBinding":null,"lastCommittedPoint":null,"startArrowhead":null,"endArrowhead":null,"points":[[0,0],[0,294.0000305175781]]},{"type":"line","version":460,"versionNonce":104653073,"isDeleted":false,"id":"uRrYpfltas6Toh9e3W1FE","fillStyle":"hachure","strokeWidth":1,"strokeStyle":"solid","roughness":0,"opacity":100,"angle":0,"x":411.0495556514421,"y":-232.9143109346104,"strokeColor":"#000000","backgroundColor":"transparent","width":0,"height":294.3333282470703,"seed":805105073,"groupIds":[],"roundness":null,"boundElements":null,"updated":1696424775188,"link":null,"locked":false,"startBinding":null,"endBinding":null,"lastCommittedPoint":null,"startArrowhead":null,"endArrowhead":null,"points":[[0,0],[0,294.3333282470703]]},{"type":"line","version":481,"versionNonce":826946687,"isDeleted":false,"id":"sf9zSmyYdkFtnVYIx9E5O","fillStyle":"hachure","strokeWidth":1,"strokeStyle":"solid","roughness":0,"opacity":100,"angle":0,"x":462.3826855342546,"y":-232.24762392289165,"strokeColor":"#000000","backgroundColor":"transparent","width":0,"height":293.6667022705078,"seed":215400927,"groupIds":[],"roundness":null,"boundElements":null,"updated":1696424775188,"link":null,"locked":false,"startBinding":null,"endBinding":null,"lastCommittedPoint":null,"startArrowhead":null,"endArrowhead":null,"points":[[0,0],[0,293.6667022705078]]},{"type":"line","version":291,"versionNonce":117479153,"isDeleted":false,"id":"Geg3egZ9-tODJ2MrxhR53","fillStyle":"hachure","strokeWidth":1,"strokeStyle":"solid","roughness":0,"opacity":100,"angle":0,"x":229.71618162800462,"y":-200.58092165238384,"strokeColor":"#000000","backgroundColor":"transparent","width":287.5441943485579,"height":0,"seed":1649807249,"groupIds":[],"roundness":null,"boundElements":null,"updated":1696424775188,"link":null,"locked":false,"startBinding":null,"endBinding":null,"lastCommittedPoint":null,"startArrowhead":null,"endArrowhead":null,"points":[[0,0],[287.5441943485579,0]]},{"type":"text","version":205,"versionNonce":1479363743,"isDeleted":false,"id":"GsCZ-YGZ95KALn-0gRzfy","fillStyle":"hachure","strokeWidth":1,"strokeStyle":"solid","roughness":0,"opacity":100,"angle":0,"x":243.71618162800462,"y":-229.0809826875401,"strokeColor":"#000000","backgroundColor":"transparent","width":13,"height":25,"seed":562114047,"groupIds":[],"roundness":null,"boundElements":null,"updated":1696424775188,"link":null,"locked":false,"fontSize":20,"fontFamily":1,"text":"x","baseline":17,"textAlign":"left","verticalAlign":"top","containerId":null,"originalText":"x"},{"type":"text","version":220,"versionNonce":93491409,"isDeleted":false,"id":"ukSq9Hp5jHQCsjcaEmLQI","fillStyle":"hachure","strokeWidth":1,"strokeStyle":"solid","roughness":0,"opacity":100,"angle":0,"x":292.38286863972337,"y":-232.0809826875401,"strokeColor":"#000000","backgroundColor":"transparent","width":11,"height":25,"seed":351270257,"groupIds":[],"roundness":null,"boundElements":null,"updated":1696424775188,"link":null,"locked":false,"fontSize":20,"fontFamily":1,"text":"y","baseline":17,"textAlign":"left","verticalAlign":"top","containerId":null,"originalText":"y"},{"type":"text","version":272,"versionNonce":2081097296,"isDeleted":false,"id":"uk_QFOMdaJm51AgyHsVLm","fillStyle":"hachure","strokeWidth":1,"strokeStyle":"solid","roughness":0,"opacity":100,"angle":0,"x":238.38280760456712,"y":-184.41429567582134,"strokeColor":"#000000","backgroundColor":"transparent","width":26,"height":224,"seed":1783174687,"groupIds":[],"roundness":null,"boundElements":null,"updated":1696425729628,"link":null,"locked":false,"fontSize":20,"fontFamily":1,"text":"x0\n\nx1\n\nx2\n\nx3\n\nx4","baseline":216,"textAlign":"left","verticalAlign":"top","containerId":null,"originalText":"x0\n\nx1\n\nx2\n\nx3\n\nx4"},{"type":"text","version":285,"versionNonce":1657489072,"isDeleted":false,"id":"XpMEZx70gs9YSrzbP0dWd","fillStyle":"hachure","strokeWidth":1,"strokeStyle":"solid","roughness":0,"opacity":100,"angle":0,"x":280.04949461628587,"y":-187.08095216996196,"strokeColor":"#000000","backgroundColor":"transparent","width":33,"height":224,"seed":185737041,"groupIds":[],"roundness":null,"boundElements":null,"updated":1696425729628,"link":null,"locked":false,"fontSize":20,"fontFamily":1,"text":"y-2\n\ny-1\n\ny0\n\ny1\n\ny2","baseline":216,"textAlign":"left","verticalAlign":"top","containerId":null,"originalText":"y-2\n\ny-1\n\ny0\n\ny1\n\ny2"},{"type":"text","version":245,"versionNonce":403435743,"isDeleted":false,"id":"WgUETkZG3LcC-h_K7SqSf","fillStyle":"hachure","strokeWidth":1,"strokeStyle":"solid","roughness":0,"opacity":100,"angle":0,"x":331.7161816280046,"y":-229.74757814652446,"strokeColor":"#000000","backgroundColor":"transparent","width":17,"height":25,"seed":1105418847,"groupIds":[],"roundness":null,"boundElements":null,"updated":1696424775188,"link":null,"locked":false,"fontSize":20,"fontFamily":1,"text":"y'","baseline":17,"textAlign":"left","verticalAlign":"top","containerId":null,"originalText":"y'"},{"type":"text","version":253,"versionNonce":865030289,"isDeleted":false,"id":"vikPci7-RYRpuT7Po3tKT","fillStyle":"hachure","strokeWidth":1,"strokeStyle":"solid","roughness":0,"opacity":100,"angle":0,"x":369.3828076045671,"y":-231.7476391816807,"strokeColor":"#000000","backgroundColor":"transparent","width":22,"height":25,"seed":1146961681,"groupIds":[],"roundness":null,"boundElements":null,"updated":1696424775188,"link":null,"locked":false,"fontSize":20,"fontFamily":1,"text":"y''","baseline":17,"textAlign":"left","verticalAlign":"top","containerId":null,"originalText":"y''"},{"type":"text","version":280,"versionNonce":205028607,"isDeleted":false,"id":"_2Goq88ssngh_yfOfYXJG","fillStyle":"hachure","strokeWidth":1,"strokeStyle":"solid","roughness":0,"opacity":100,"angle":0,"x":422.3829296748796,"y":-231.0809826875401,"strokeColor":"#000000","backgroundColor":"transparent","width":27,"height":25,"seed":711374463,"groupIds":[],"roundness":null,"boundElements":null,"updated":1696424775188,"link":null,"locked":false,"fontSize":20,"fontFamily":1,"text":"y'''","baseline":17,"textAlign":"left","verticalAlign":"top","containerId":null,"originalText":"y'''"},{"type":"text","version":277,"versionNonce":1331238513,"isDeleted":false,"id":"TSL4HMpLtsZ9KQk7joOa-","fillStyle":"hachure","strokeWidth":1,"strokeStyle":"solid","roughness":0,"opacity":100,"angle":0,"x":471.0495556514421,"y":-230.41429567582134,"strokeColor":"#000000","backgroundColor":"transparent","width":33,"height":25,"seed":1639149265,"groupIds":[],"roundness":null,"boundElements":null,"updated":1696424775188,"link":null,"locked":false,"fontSize":20,"fontFamily":1,"text":"y''''","baseline":17,"textAlign":"left","verticalAlign":"top","containerId":null,"originalText":"y''''"},{"type":"text","version":224,"versionNonce":457994687,"isDeleted":false,"id":"HOuyimn2Itb3C_df-CKhr","fillStyle":"hachure","strokeWidth":1,"strokeStyle":"solid","roughness":0,"opacity":100,"angle":0,"x":232.04955565144212,"y":-269.080967428751,"strokeColor":"#000000","backgroundColor":"transparent","width":298,"height":25,"seed":698331871,"groupIds":[],"roundness":null,"boundElements":null,"updated":1696424778966,"link":null,"locked":false,"fontSize":20,"fontFamily":1,"text":"Gauss Forward and Backward","baseline":17,"textAlign":"left","verticalAlign":"top","containerId":null,"originalText":"Gauss Forward and Backward"},{"type":"text","version":411,"versionNonce":2004204624,"isDeleted":false,"id":"LuoVikH--4wJZ--jyTWvz","fillStyle":"hachure","strokeWidth":1,"strokeStyle":"solid","roughness":0,"opacity":100,"angle":0,"x":324.760498046875,"y":-161.00006103515625,"strokeColor":"#000000","backgroundColor":"transparent","width":33,"height":174,"seed":1595723793,"groupIds":[],"roundness":null,"boundElements":null,"updated":1696425729630,"link":null,"locked":false,"fontSize":20,"fontFamily":1,"text":"y-2\n\ny-1\n\ny0\n\ny1","baseline":166,"textAlign":"left","verticalAlign":"top","containerId":null,"originalText":"y-2\n\ny-1\n\ny0\n\ny1"},{"type":"text","version":564,"versionNonce":823062704,"isDeleted":false,"id":"nRJA3X7BWKqoGyBXywQkr","fillStyle":"hachure","strokeWidth":1,"strokeStyle":"solid","roughness":0,"opacity":100,"angle":0,"x":371.4271240234375,"y":-138.1666259765625,"strokeColor":"#000000","backgroundColor":"transparent","width":33,"height":124,"seed":886093791,"groupIds":[],"roundness":null,"boundElements":null,"updated":1696425729630,"link":null,"locked":false,"fontSize":20,"fontFamily":1,"text":"y-2\n\ny-1\n\ny0","baseline":116,"textAlign":"left","verticalAlign":"top","containerId":null,"originalText":"y-2\n\ny-1\n\ny0"},{"type":"text","version":680,"versionNonce":1612296784,"isDeleted":false,"id":"t6ZMGmYF7HDh8TtAbAtCp","fillStyle":"hachure","strokeWidth":1,"strokeStyle":"solid","roughness":0,"opacity":100,"angle":0,"x":421.4271240234375,"y":-111.16668701171875,"strokeColor":"#000000","backgroundColor":"transparent","width":33,"height":75,"seed":1920739263,"groupIds":[],"roundness":null,"boundElements":null,"updated":1696425729630,"link":null,"locked":false,"fontSize":20,"fontFamily":1,"text":"y-2\n\ny-1","baseline":67,"textAlign":"left","verticalAlign":"top","containerId":null,"originalText":"y-2\n\ny-1"},{"type":"text","version":723,"versionNonce":495520095,"isDeleted":false,"id":"X3rJXTGy6AYc4W3NaJP1D","fillStyle":"hachure","strokeWidth":1,"strokeStyle":"solid","roughness":0,"opacity":100,"angle":0,"x":470.427001953125,"y":-82.66668701171875,"strokeColor":"#000000","backgroundColor":"transparent","width":34,"height":25,"seed":2117030783,"groupIds":[],"roundness":null,"boundElements":null,"updated":1696424775188,"link":null,"locked":false,"fontSize":20,"fontFamily":1,"text":"y-2","baseline":17,"textAlign":"left","verticalAlign":"top","containerId":null,"originalText":"y-2"},{"id":"cv-JHe2gWJbaUPgAoNYbe","type":"line","x":291.2603759765625,"y":-72.6666259765625,"width":194,"height":26.6666259765625,"angle":0,"strokeColor":"#862e9c","backgroundColor":"transparent","fillStyle":"hachure","strokeWidth":1,"strokeStyle":"solid","roughness":0,"opacity":100,"groupIds":[],"roundness":null,"seed":1320011071,"version":306,"versionNonce":577634321,"isDeleted":false,"boundElements":null,"updated":1696424775188,"link":null,"locked":false,"points":[[0,0],[42,-23.3333740234375],[89.3333740234375,-1.3333740234375],[145.3333740234375,-24],[194,2.6666259765625]],"lastCommittedPoint":[194,2.6666259765625],"startBinding":null,"endBinding":null,"startArrowhead":null,"endArrowhead":null},{"id":"I16tpbvW4pVzMlDNIasrB","type":"line","x":292.59375,"y":-72,"width":190.6666259765625,"height":28.66668701171875,"angle":0,"strokeColor":"#087f5b","backgroundColor":"transparent","fillStyle":"hachure","strokeWidth":1,"strokeStyle":"solid","roughness":0,"opacity":100,"groupIds":[],"roundness":null,"seed":141151199,"version":317,"versionNonce":58623359,"isDeleted":false,"boundElements":null,"updated":1696424775188,"link":null,"locked":false,"points":[[0,0],[42,27.3333740234375],[90,-1.33331298828125],[139.3333740234375,26.66668701171875],[190.6666259765625,2.66668701171875]],"lastCommittedPoint":[190.6666259765625,2.66668701171875],"startBinding":null,"endBinding":null,"startArrowhead":null,"endArrowhead":null},{"id":"DT5cLk382j919OBQ6hFRx","type":"text","x":539.5474853515625,"y":-204.6817626953125,"width":106,"height":25,"angle":0,"strokeColor":"#862e9c","backgroundColor":"transparent","fillStyle":"hachure","strokeWidth":1,"strokeStyle":"solid","roughness":0,"opacity":100,"groupIds":[],"roundness":null,"seed":1781433520,"version":59,"versionNonce":858796208,"isDeleted":false,"boundElements":null,"updated":1696425740512,"link":null,"locked":false,"text":"Backwards","fontSize":20,"fontFamily":1,"textAlign":"left","verticalAlign":"top","baseline":17,"containerId":null,"originalText":"Backwards"},{"id":"PVSzzyCPjfypEsiO-3jQb","type":"text","x":540.668701171875,"y":-172.92422485351562,"width":79,"height":25,"angle":0,"strokeColor":"#087f5b","backgroundColor":"transparent","fillStyle":"hachure","strokeWidth":1,"strokeStyle":"solid","roughness":0,"opacity":100,"groupIds":[],"roundness":null,"seed":1459145296,"version":47,"versionNonce":1164368464,"isDeleted":false,"boundElements":null,"updated":1696425749668,"link":null,"locked":false,"text":"Forward","fontSize":20,"fontFamily":1,"textAlign":"left","verticalAlign":"top","baseline":17,"containerId":null,"originalText":"Forward"}],"appState":{"showWelcomeScreen":true,"theme":"dark","collaborators":[],"currentChartType":"bar","currentItemBackgroundColor":"transparent","currentItemEndArrowhead":"arrow","currentItemFillStyle":"hachure","currentItemFontFamily":1,"currentItemFontSize":20,"currentItemOpacity":100,"currentItemRoughness":0,"currentItemStartArrowhead":null,"currentItemStrokeColor":"#087f5b","currentItemRoundness":"sharp","currentItemStrokeStyle":"solid","currentItemStrokeWidth":1,"currentItemTextAlign":"left","cursorButton":"up","draggingElement":null,"editingElement":null,"editingGroupId":null,"editingLinearElement":null,"activeTool":{"type":"selection","customType":null,"locked":false,"lastActiveTool":null},"penMode":false,"penDetected":false,"errorMessage":null,"exportBackground":true,"exportScale":1,"exportEmbedScene":false,"exportWithDarkMode":false,"fileHandle":null,"gridSize":null,"isBindingEnabled":true,"isSidebarDocked":false,"isLoading":false,"isResizing":false,"isRotating":false,"lastPointerDownWith":"mouse","multiElement":null,"name":"Untitled-2023-09-04-1241","contextMenu":null,"openMenu":null,"openPopup":null,"openSidebar":null,"openDialog":null,"pasteDialog":{"shown":false,"data":null},"previousSelectedElementIds":{"PVSzzyCPjfypEsiO-3jQb":true,"HbKRlPCCXvOxdperK5Eq_":true},"resizingElement":null,"scrolledOutside":false,"scrollX":0,"scrollY":360,"selectedElementIds":{"qvWxX5envhHIoI4NpRvEo":true},"selectedGroupIds":{},"selectionElement":null,"shouldCacheIgnoreZoom":false,"showStats":false,"startBoundElement":null,"suggestedBindings":[],"toast":null,"viewBackgroundColor":"#ffffff","zenModeEnabled":false,"zoom":{"value":1},"viewModeEnabled":false,"pendingImageElementId":null,"showHyperlinkPopup":false,"selectedLinearElement":null,"offsetLeft":578.9677734375,"offsetTop":130.60604858398438,"width":973.1533203125,"height":643.3333129882812},"files":{},"svg":"<svg version=\"1.1\" xmlns=\"http://www.w3.org/2000/svg\" viewBox=\"0 0 425.8313037235579 341.83338928222656\" width=\"425.8313037235579\" height=\"341.83338928222656\">\n  <!-- svg-source:excalidraw -->\n  \n  <defs>\n    <style class=\"style-fonts\">\n      @font-face {\n        font-family: \"Virgil\";\n        src: url(\"http://192.168.29.44:7040/node_modules/@excalidraw/excalidraw/dist//dist/excalidraw-assets/Virgil.woff2\");\n      }\n      @font-face {\n        font-family: \"Cascadia\";\n        src: url(\"http://192.168.29.44:7040/node_modules/@excalidraw/excalidraw/dist//dist/excalidraw-assets/Cascadia.woff2\");\n      }\n    </style>\n  </defs>\n  <rect x=\"0\" y=\"0\" width=\"425.8313037235579\" height=\"341.83338928222656\" fill=\"#ffffff\"></rect><g stroke-linecap=\"round\" transform=\"translate(5 40.83335876464844) rotate(0 143.66668701171875 148.00001525878906)\"><path d=\"M0 0 C99.57 0, 199.14 0, 287.33 0 M0 0 C80.4 0, 160.8 0, 287.33 0 M287.33 0 C287.33 115.63, 287.33 231.26, 287.33 296 M287.33 0 C287.33 70.38, 287.33 140.75, 287.33 296 M287.33 296 C212.72 296, 138.1 296, 0 296 M287.33 296 C194.93 296, 102.53 296, 0 296 M0 296 C0 208.44, 0 120.89, 0 0 M0 296 C0 183.01, 0 70.01, 0 0\" stroke=\"#000000\" stroke-width=\"1\" fill=\"none\"></path></g><g stroke-linecap=\"round\"><g transform=\"translate(49.66668701171875 40.83332824707031) rotate(0 0 147.6666717529297)\"><path d=\"M0 0 C0 62.61, 0 125.22, 0 295.33 M0 0 C0 89.47, 0 178.94, 0 295.33\" stroke=\"#000000\" stroke-width=\"1\" fill=\"none\"></path></g></g><mask></mask><g stroke-linecap=\"round\"><g transform=\"translate(93.66668701171875 41.50001525878906) rotate(0 0 147.3333282470703)\"><path d=\"M0 0 C0 103.73, 0 207.45, 0 294.67 M0 0 C0 90.41, 0 180.82, 0 294.67\" stroke=\"#000000\" stroke-width=\"1\" fill=\"none\"></path></g></g><mask></mask><g stroke-linecap=\"round\"><g transform=\"translate(136.3333740234375 41.50001525878906) rotate(0 0 147.00001525878906)\"><path d=\"M0 0 C0 80.84, 0 161.69, 0 294 M0 0 C0 78.28, 0 156.56, 0 294\" stroke=\"#000000\" stroke-width=\"1\" fill=\"none\"></path></g></g><mask></mask><g stroke-linecap=\"round\"><g transform=\"translate(186.3333740234375 41.166656494140625) rotate(0 0 147.16666412353516)\"><path d=\"M0 0 C0 64.77, 0 129.54, 0 294.33 M0 0 C0 72.39, 0 144.77, 0 294.33\" stroke=\"#000000\" stroke-width=\"1\" fill=\"none\"></path></g></g><mask></mask><g stroke-linecap=\"round\"><g transform=\"translate(237.66650390625 41.833343505859375) rotate(0 0 146.8333511352539)\"><path d=\"M0 0 C0 103.86, 0 207.71, 0 293.67 M0 0 C0 87.37, 0 174.74, 0 293.67\" stroke=\"#000000\" stroke-width=\"1\" fill=\"none\"></path></g></g><mask></mask><g stroke-linecap=\"round\"><g transform=\"translate(5 73.50004577636719) rotate(0 143.77209717427894 0)\"><path d=\"M0 0 C72.56 0, 145.12 0, 287.54 0 M0 0 C101.4 0, 202.81 0, 287.54 0\" stroke=\"#000000\" stroke-width=\"1\" fill=\"none\"></path></g></g><mask></mask><g transform=\"translate(19 44.99998474121094) rotate(0 6.5 12.5)\"><text x=\"0\" y=\"17\" font-family=\"Virgil, Segoe UI Emoji\" font-size=\"20px\" fill=\"#000000\" text-anchor=\"start\" style=\"white-space: pre;\" direction=\"ltr\">x</text></g><g transform=\"translate(67.66668701171875 41.99998474121094) rotate(0 5.5 12.5)\"><text x=\"0\" y=\"17\" font-family=\"Virgil, Segoe UI Emoji\" font-size=\"20px\" fill=\"#000000\" text-anchor=\"start\" style=\"white-space: pre;\" direction=\"ltr\">y</text></g><g transform=\"translate(13.6666259765625 89.66667175292969) rotate(0 13 112)\"><text x=\"0\" y=\"16.88888888888889\" font-family=\"Virgil, Segoe UI Emoji\" font-size=\"20px\" fill=\"#000000\" text-anchor=\"start\" style=\"white-space: pre;\" direction=\"ltr\">x0</text><text x=\"0\" y=\"41.77777777777778\" font-family=\"Virgil, Segoe UI Emoji\" font-size=\"20px\" fill=\"#000000\" text-anchor=\"start\" style=\"white-space: pre;\" direction=\"ltr\"></text><text x=\"0\" y=\"66.66666666666667\" font-family=\"Virgil, Segoe UI Emoji\" font-size=\"20px\" fill=\"#000000\" text-anchor=\"start\" style=\"white-space: pre;\" direction=\"ltr\">x1</text><text x=\"0\" y=\"91.55555555555556\" font-family=\"Virgil, Segoe UI Emoji\" font-size=\"20px\" fill=\"#000000\" text-anchor=\"start\" style=\"white-space: pre;\" direction=\"ltr\"></text><text x=\"0\" y=\"116.44444444444444\" font-family=\"Virgil, Segoe UI Emoji\" font-size=\"20px\" fill=\"#000000\" text-anchor=\"start\" style=\"white-space: pre;\" direction=\"ltr\">x2</text><text x=\"0\" y=\"141.33333333333334\" font-family=\"Virgil, Segoe UI Emoji\" font-size=\"20px\" fill=\"#000000\" text-anchor=\"start\" style=\"white-space: pre;\" direction=\"ltr\"></text><text x=\"0\" y=\"166.22222222222223\" font-family=\"Virgil, Segoe UI Emoji\" font-size=\"20px\" fill=\"#000000\" text-anchor=\"start\" style=\"white-space: pre;\" direction=\"ltr\">x3</text><text x=\"0\" y=\"191.11111111111111\" font-family=\"Virgil, Segoe UI Emoji\" font-size=\"20px\" fill=\"#000000\" text-anchor=\"start\" style=\"white-space: pre;\" direction=\"ltr\"></text><text x=\"0\" y=\"216\" font-family=\"Virgil, Segoe UI Emoji\" font-size=\"20px\" fill=\"#000000\" text-anchor=\"start\" style=\"white-space: pre;\" direction=\"ltr\">x4</text></g><g transform=\"translate(55.33331298828125 87.00001525878906) rotate(0 16.5 112)\"><text x=\"0\" y=\"16.88888888888889\" font-family=\"Virgil, Segoe UI Emoji\" font-size=\"20px\" fill=\"#000000\" text-anchor=\"start\" style=\"white-space: pre;\" direction=\"ltr\">y-2</text><text x=\"0\" y=\"41.77777777777778\" font-family=\"Virgil, Segoe UI Emoji\" font-size=\"20px\" fill=\"#000000\" text-anchor=\"start\" style=\"white-space: pre;\" direction=\"ltr\"></text><text x=\"0\" y=\"66.66666666666667\" font-family=\"Virgil, Segoe UI Emoji\" font-size=\"20px\" fill=\"#000000\" text-anchor=\"start\" style=\"white-space: pre;\" direction=\"ltr\">y-1</text><text x=\"0\" y=\"91.55555555555556\" font-family=\"Virgil, Segoe UI Emoji\" font-size=\"20px\" fill=\"#000000\" text-anchor=\"start\" style=\"white-space: pre;\" direction=\"ltr\"></text><text x=\"0\" y=\"116.44444444444444\" font-family=\"Virgil, Segoe UI Emoji\" font-size=\"20px\" fill=\"#000000\" text-anchor=\"start\" style=\"white-space: pre;\" direction=\"ltr\">y0</text><text x=\"0\" y=\"141.33333333333334\" font-family=\"Virgil, Segoe UI Emoji\" font-size=\"20px\" fill=\"#000000\" text-anchor=\"start\" style=\"white-space: pre;\" direction=\"ltr\"></text><text x=\"0\" y=\"166.22222222222223\" font-family=\"Virgil, Segoe UI Emoji\" font-size=\"20px\" fill=\"#000000\" text-anchor=\"start\" style=\"white-space: pre;\" direction=\"ltr\">y1</text><text x=\"0\" y=\"191.11111111111111\" font-family=\"Virgil, Segoe UI Emoji\" font-size=\"20px\" fill=\"#000000\" text-anchor=\"start\" style=\"white-space: pre;\" direction=\"ltr\"></text><text x=\"0\" y=\"216\" font-family=\"Virgil, Segoe UI Emoji\" font-size=\"20px\" fill=\"#000000\" text-anchor=\"start\" style=\"white-space: pre;\" direction=\"ltr\">y2</text></g><g transform=\"translate(107 44.33338928222656) rotate(0 8.5 12.5)\"><text x=\"0\" y=\"17\" font-family=\"Virgil, Segoe UI Emoji\" font-size=\"20px\" fill=\"#000000\" text-anchor=\"start\" style=\"white-space: pre;\" direction=\"ltr\">y'</text></g><g transform=\"translate(144.6666259765625 42.33332824707031) rotate(0 11 12.5)\"><text x=\"0\" y=\"17\" font-family=\"Virgil, Segoe UI Emoji\" font-size=\"20px\" fill=\"#000000\" text-anchor=\"start\" style=\"white-space: pre;\" direction=\"ltr\">y''</text></g><g transform=\"translate(197.666748046875 42.99998474121094) rotate(0 13.5 12.5)\"><text x=\"0\" y=\"17\" font-family=\"Virgil, Segoe UI Emoji\" font-size=\"20px\" fill=\"#000000\" text-anchor=\"start\" style=\"white-space: pre;\" direction=\"ltr\">y'''</text></g><g transform=\"translate(246.3333740234375 43.66667175292969) rotate(0 16.5 12.5)\"><text x=\"0\" y=\"17\" font-family=\"Virgil, Segoe UI Emoji\" font-size=\"20px\" fill=\"#000000\" text-anchor=\"start\" style=\"white-space: pre;\" direction=\"ltr\">y''''</text></g><g transform=\"translate(7.3333740234375 5) rotate(0 149 12.5)\"><text x=\"0\" y=\"17\" font-family=\"Virgil, Segoe UI Emoji\" font-size=\"20px\" fill=\"#000000\" text-anchor=\"start\" style=\"white-space: pre;\" direction=\"ltr\">Gauss Forward and Backward</text></g><g transform=\"translate(100.04431641887038 113.08090639359477) rotate(0 16.5 87)\"><text x=\"0\" y=\"16.857142857142858\" font-family=\"Virgil, Segoe UI Emoji\" font-size=\"20px\" fill=\"#000000\" text-anchor=\"start\" style=\"white-space: pre;\" direction=\"ltr\">y-2</text><text x=\"0\" y=\"41.714285714285715\" font-family=\"Virgil, Segoe UI Emoji\" font-size=\"20px\" fill=\"#000000\" text-anchor=\"start\" style=\"white-space: pre;\" direction=\"ltr\"></text><text x=\"0\" y=\"66.57142857142857\" font-family=\"Virgil, Segoe UI Emoji\" font-size=\"20px\" fill=\"#000000\" text-anchor=\"start\" style=\"white-space: pre;\" direction=\"ltr\">y-1</text><text x=\"0\" y=\"91.42857142857143\" font-family=\"Virgil, Segoe UI Emoji\" font-size=\"20px\" fill=\"#000000\" text-anchor=\"start\" style=\"white-space: pre;\" direction=\"ltr\"></text><text x=\"0\" y=\"116.28571428571429\" font-family=\"Virgil, Segoe UI Emoji\" font-size=\"20px\" fill=\"#000000\" text-anchor=\"start\" style=\"white-space: pre;\" direction=\"ltr\">y0</text><text x=\"0\" y=\"141.14285714285714\" font-family=\"Virgil, Segoe UI Emoji\" font-size=\"20px\" fill=\"#000000\" text-anchor=\"start\" style=\"white-space: pre;\" direction=\"ltr\"></text><text x=\"0\" y=\"166\" font-family=\"Virgil, Segoe UI Emoji\" font-size=\"20px\" fill=\"#000000\" text-anchor=\"start\" style=\"white-space: pre;\" direction=\"ltr\">y1</text></g><g transform=\"translate(146.71094239543288 135.91434145218852) rotate(0 16.5 62)\"><text x=\"0\" y=\"16.8\" font-family=\"Virgil, Segoe UI Emoji\" font-size=\"20px\" fill=\"#000000\" text-anchor=\"start\" style=\"white-space: pre;\" direction=\"ltr\">y-2</text><text x=\"0\" y=\"41.6\" font-family=\"Virgil, Segoe UI Emoji\" font-size=\"20px\" fill=\"#000000\" text-anchor=\"start\" style=\"white-space: pre;\" direction=\"ltr\"></text><text x=\"0\" y=\"66.4\" font-family=\"Virgil, Segoe UI Emoji\" font-size=\"20px\" fill=\"#000000\" text-anchor=\"start\" style=\"white-space: pre;\" direction=\"ltr\">y-1</text><text x=\"0\" y=\"91.2\" font-family=\"Virgil, Segoe UI Emoji\" font-size=\"20px\" fill=\"#000000\" text-anchor=\"start\" style=\"white-space: pre;\" direction=\"ltr\"></text><text x=\"0\" y=\"116\" font-family=\"Virgil, Segoe UI Emoji\" font-size=\"20px\" fill=\"#000000\" text-anchor=\"start\" style=\"white-space: pre;\" direction=\"ltr\">y0</text></g><g transform=\"translate(196.71094239543288 162.91428041703227) rotate(0 16.5 37.5)\"><text x=\"0\" y=\"17\" font-family=\"Virgil, Segoe UI Emoji\" font-size=\"20px\" fill=\"#000000\" text-anchor=\"start\" style=\"white-space: pre;\" direction=\"ltr\">y-2</text><text x=\"0\" y=\"42\" font-family=\"Virgil, Segoe UI Emoji\" font-size=\"20px\" fill=\"#000000\" text-anchor=\"start\" style=\"white-space: pre;\" direction=\"ltr\"></text><text x=\"0\" y=\"67\" font-family=\"Virgil, Segoe UI Emoji\" font-size=\"20px\" fill=\"#000000\" text-anchor=\"start\" style=\"white-space: pre;\" direction=\"ltr\">y-1</text></g><g transform=\"translate(245.71082032512038 191.41428041703227) rotate(0 17 12.5)\"><text x=\"0\" y=\"17\" font-family=\"Virgil, Segoe UI Emoji\" font-size=\"20px\" fill=\"#000000\" text-anchor=\"start\" style=\"white-space: pre;\" direction=\"ltr\">y-2</text></g><g stroke-linecap=\"round\"><g transform=\"translate(66.54419434855788 201.41434145218852) rotate(0 97 -10.66668701171875)\"><path d=\"M0 0 C9.44 -5.25, 18.89 -10.49, 42 -23.33 M0 0 C9.56 -5.31, 19.13 -10.63, 42 -23.33 M42 -23.33 C55.98 -16.83, 69.96 -10.34, 89.33 -1.33 M42 -23.33 C57.6 -16.08, 73.21 -8.83, 89.33 -1.33 M89.33 -1.33 C105.32 -7.8, 121.3 -14.27, 145.33 -24 M89.33 -1.33 C103.07 -6.89, 116.8 -12.45, 145.33 -24 M145.33 -24 C164.62 -13.43, 183.9 -2.87, 194 2.67 M145.33 -24 C155.15 -18.62, 164.96 -13.25, 194 2.67\" stroke=\"#862e9c\" stroke-width=\"1\" fill=\"none\"></path></g></g><mask></mask><g stroke-linecap=\"round\"><g transform=\"translate(67.87756837199538 202.08096742875102) rotate(0 95.33331298828125 13.000030517578125)\"><path d=\"M0 0 C15.02 9.77, 30.03 19.54, 42 27.33 M0 0 C14.09 9.17, 28.18 18.34, 42 27.33 M42 27.33 C57.39 18.14, 72.79 8.95, 90 -1.33 M42 27.33 C60.95 16.01, 79.91 4.7, 90 -1.33 M90 -1.33 C102.27 5.63, 114.55 12.6, 139.33 26.67 M90 -1.33 C100.12 4.41, 110.23 10.15, 139.33 26.67 M139.33 26.67 C153.41 20.09, 167.48 13.51, 190.67 2.67 M139.33 26.67 C153.83 19.89, 168.32 13.11, 190.67 2.67\" stroke=\"#087f5b\" stroke-width=\"1\" fill=\"none\"></path></g></g><mask></mask><g transform=\"translate(314.8313037235579 69.39920473343852) rotate(0 53 12.5)\"><text x=\"0\" y=\"17\" font-family=\"Virgil, Segoe UI Emoji\" font-size=\"20px\" fill=\"#862e9c\" text-anchor=\"start\" style=\"white-space: pre;\" direction=\"ltr\">Backwards</text></g><g transform=\"translate(315.9525195438704 101.1567425752354) rotate(0 39.5 12.5)\"><text x=\"0\" y=\"17\" font-family=\"Virgil, Segoe UI Emoji\" font-size=\"20px\" fill=\"#087f5b\" text-anchor=\"start\" style=\"white-space: pre;\" direction=\"ltr\">Forward</text></g></svg>"}